gammasimtools-0.26.0.dist-info/licenses/LICENSE
simtools/__init__.py
simtools/_version.py
simtools/application_control.py
simtools/constants.py
simtools/dependencies.py
simtools/settings.py
simtools/simulator.py
simtools/telescope_trigger_rates.py
simtools/version.py
simtools/applications/calculate_incident_angles.py
simtools/applications/convert_all_model_parameters_from_simtel.py
simtools/applications/convert_geo_coordinates_of_array_elements.py
simtools/applications/convert_model_parameter_from_simtel.py
simtools/applications/db_add_file_to_db.py
simtools/applications/db_add_simulation_model_from_repository_to_db.py
simtools/applications/db_add_value_from_json_to_db.py
simtools/applications/db_generate_compound_indexes.py
simtools/applications/db_get_array_layouts_from_db.py
simtools/applications/db_get_file_from_db.py
simtools/applications/db_get_parameter_from_db.py
simtools/applications/db_inspect_databases.py
simtools/applications/db_upload_model_repository.py
simtools/applications/derive_ctao_array_layouts.py
simtools/applications/derive_mirror_rnda.py
simtools/applications/derive_photon_electron_spectrum.py
simtools/applications/derive_psf_parameters.py
simtools/applications/derive_pulse_shape_parameters.py
simtools/applications/derive_trigger_rates.py
simtools/applications/docs_produce_array_element_report.py
simtools/applications/docs_produce_calibration_reports.py
simtools/applications/docs_produce_model_parameter_reports.py
simtools/applications/docs_produce_simulation_configuration_report.py
simtools/applications/generate_array_config.py
simtools/applications/generate_corsika_histograms.py
simtools/applications/generate_default_metadata.py
simtools/applications/generate_regular_arrays.py
simtools/applications/generate_simtel_event_data.py
simtools/applications/maintain_simulation_model_add_production.py
simtools/applications/maintain_simulation_model_compare_productions.py
simtools/applications/maintain_simulation_model_verify_production_tables.py
gammasimtools-0.26.0.dist-info/METADATA
gammasimtools-0.26.0.dist-info/WHEEL
gammasimtools-0.26.0.dist-info/entry_points.txt
gammasimtools-0.26.0.dist-info/top_level.txt
gammasimtools-0.26.0.dist-info/RECORD
