Metadata-Version: 2.4
Name: gammasimtools
Version: 0.26.0
Summary: Tools for the Simulation System of the CTA Observatory
Author-email: simtools developers <simtools-developer@desy.de>
License-Expression: BSD-3-Clause
Project-URL: bug tracker, https://github.com/gammasim/simtools/issues
Project-URL: documentation, https://gammasim.github.io/simtools/
Project-URL: repository, https://github.com/gammasim/simtools
Classifier: Intended Audience :: Science/Research
Classifier: Operating System :: OS Independent
Classifier: Programming Language :: Python :: 3 :: Only
Classifier: Programming Language :: Python :: 3.12
Classifier: Programming Language :: Python :: 3.13
Classifier: Programming Language :: Python :: 3.14
Classifier: Topic :: Scientific/Engineering :: Astronomy
Requires-Python: >=3.12
License-File: LICENSE
Requires-Dist: adjusttext
Requires-Dist: astropy
Requires-Dist: boost-histogram
Requires-Dist: ctao-dpps-cosmic-ray-spectra
Requires-Dist: ctapipe
Requires-Dist: eventio
Requires-Dist: h5py
Requires-Dist: jsonschema
Requires-Dist: matplotlib
Requires-Dist: numpy
Requires-Dist: particle
Requires-Dist: pymongo
Requires-Dist: pyproj
Requires-Dist: python-dotenv
Requires-Dist: pyyaml
Requires-Dist: scipy
Requires-Dist: toml
Provides-Extra: dev
Requires-Dist: pre-commit; extra == "dev"
Requires-Dist: pylint; extra == "dev"
Requires-Dist: ruff; extra == "dev"
Provides-Extra: doc
Requires-Dist: myst-parser; extra == "doc"
Requires-Dist: numpydoc; extra == "doc"
Requires-Dist: pydata-sphinx-theme; extra == "doc"
Requires-Dist: sphinx; extra == "doc"
Requires-Dist: sphinx-design; extra == "doc"
Requires-Dist: towncrier; extra == "doc"
Provides-Extra: tests
Requires-Dist: pytest; extra == "tests"
Requires-Dist: pytest-cov; extra == "tests"
Requires-Dist: pytest-mock; extra == "tests"
Requires-Dist: pytest-profiling; extra == "tests"
Requires-Dist: pytest-random-order; extra == "tests"
Requires-Dist: pytest-repeat; extra == "tests"
Requires-Dist: pytest-requirements; extra == "tests"
Requires-Dist: pytest-retry; extra == "tests"
Requires-Dist: pytest-xdist; extra == "tests"
Dynamic: license-file
